hypnos/__init__.py
hypnos/dynamic.py
hypnos/data/Physionet.py
hypnos/data/__init__.py
hypnos/hypnograms/Hypnogram.py
hypnos/hypnograms/MarkovChain.py
hypnos/hypnograms/__init__.py
hypnos/pipelines/__init__.py
hypnos/pipelines/spectral/BandPowerWelch.py
hypnos/pipelines/spectral/__init__.py
hypnos-0.0.6.dist-info/LICENSE
hypnos-0.0.6.dist-info/METADATA
hypnos-0.0.6.dist-info/WHEEL
hypnos-0.0.6.dist-info/top_level.txt
hypnos-0.0.6.dist-info/RECORD
